ups_0auth_code/__init__.py
ups_0auth_code/sdk.py
ups_0auth_code/hooks/__init__.py
ups_0auth_code/hooks/hook.py
ups_0auth_code/models/__init__.py
ups_0auth_code/models/base.py
ups_0auth_code/models/generate_token_request.py
ups_0auth_code/models/generate_token_success_response.py
ups_0auth_code/models/refresh_token_request.py
ups_0auth_code/models/refresh_token_success_response.py
ups_0auth_code/models/utils/cast_models.py
ups_0auth_code/models/utils/json_map.py
ups_0auth_code/net/__init__.py
ups_0auth_code/net/environment/__init__.py
ups_0auth_code/net/environment/environment.py
ups_0auth_code/net/headers/__init__.py
ups_0auth_code/net/headers/base_header.py
ups_0auth_code/net/headers/basic_auth.py
ups_0auth_code/net/request_chain/__init__.py
ups_0auth_code/net/request_chain/request_chain.py
ups_0auth_code/net/request_chain/handlers/__init__.py
ups_0auth_code/net/request_chain/handlers/base_handler.py
ups_0auth_code/net/request_chain/handlers/hook_handler.py
ups_0auth_code/net/request_chain/handlers/http_handler.py
ups_0auth_code/net/request_chain/handlers/retry_handler.py
ups_0auth_code/net/transport/__init__.py
ups_0auth_code/net/transport/request.py
ups_0auth_code/net/transport/request_error.py
ups_0auth_code/net/transport/response.py
ups_0auth_code/net/transport/serializer.py
ups_0auth_code/net/transport/utils.py
ups_0auth_code/services/__init__.py
ups_0auth_code/services/authorize.py
ups_0auth_code/services/refresh.py
ups_0auth_code/services/token.py
ups_0auth_code/services/utils/base_service.py
ups_0auth_code/services/utils/default_headers.py
ups_0auth_code/services/utils/validator.py
ups_0auth_auth_code-1.0.0.dist-info/LICENSE
ups_0auth_auth_code-1.0.0.dist-info/METADATA
ups_0auth_auth_code-1.0.0.dist-info/WHEEL
ups_0auth_auth_code-1.0.0.dist-info/top_level.txt
ups_0auth_auth_code-1.0.0.dist-info/RECORD
