Metadata-Version: 2.1
Name: ups-0auth-auth-code
Version: 1.0.0
Summary: The UPS OAuth Authorization Code API helps integrate UPS services into your business application for providing the service your application grants your customers.
License: MIT
Requires-Python: >=3.7
License-File: LICENSE
Requires-Dist: requests >=2.31.0
